[
    {
        "time": 0,
        "tipTime": 3,
        "glod": 0,
        "spawns": [
            {
                "delay": 0,
                "interval": 1,
                "creep": 1,
                "path": "path_1_1",
                "count": 3
            },
            {
                "delay": 3,
                "interval": 1,
                "creep": 1,
                "path": "path_1_0",
                "count": 3
            },
            {
                "delay": 6,
                "interval": 1,
                "creep": 1,
                "path": "path_1_2",
                "count": 3
            }
        ]
    },
    {
        "time": 10,
        "tipTime": 6,
        "glod": 200,
        "spawns": [
            {
                "delay": 0,
                "interval": 1,
                "creep": 1,
                "path": "path_1_1",
                "count": 3
            }
        ]
    }
]